nectarengine/__init__.py
nectarengine/api.py
nectarengine/cli.py
nectarengine/collection.py
nectarengine/exceptions.py
nectarengine/market.py
nectarengine/nft.py
nectarengine/nftmarket.py
nectarengine/nfts.py
nectarengine/nodeslist.py
nectarengine/pool.py
nectarengine/poolobject.py
nectarengine/rpc.py
nectarengine/tokenobject.py
nectarengine/tokens.py
nectarengine/version.py
nectarengine/wallet.py
nectarengine-0.1.4.dist-info/METADATA
nectarengine-0.1.4.dist-info/WHEEL
nectarengine-0.1.4.dist-info/entry_points.txt
nectarengine-0.1.4.dist-info/licenses/LICENSE
nectarengine-0.1.4.dist-info/RECORD
