Metadata-Version: 2.4
Name: nectarengine
Version: 0.1.4
Summary: command line tool and python library for sending hive engine tokens
Project-URL: Bug Tracker, https://github.com/thecrazygm/nectarengine/issues
Project-URL: Documentation, https://nectarengine.readthedocs.io
Project-URL: Homepage, https://github.com/thecrazygm/nectarengine
Author-email: Michael Garcia <thecrazygm@gmail.com>, Holger Nahrstaedt <nahrstaedt@gmail.com>
Maintainer-email: Michael Garcia <thecrazygm@gmail.com>
License: MIT License
License-File: LICENSE
Keywords: hive,nft,tools
Classifier: Development Status :: 4 - Beta
Classifier: Intended Audience :: Developers
Classifier: License :: OSI Approved :: MIT License
Classifier: Operating System :: OS Independent
Classifier: Programming Language :: Python
Classifier: Programming Language :: Python :: 3
Classifier: Programming Language :: Python :: 3.12
Classifier: Programming Language :: Python :: 3.13
Requires-Python: >=3.10
Requires-Dist: hive-nectar
Requires-Dist: requests
